LICENSE.txt
README.md
setup.py
gym_sf/__init__.py
gym_sf.egg-info/PKG-INFO
gym_sf.egg-info/SOURCES.txt
gym_sf.egg-info/dependency_links.txt
gym_sf.egg-info/requires.txt
gym_sf.egg-info/top_level.txt
gym_sf/four_room/__init__.py
gym_sf/four_room/example.py
gym_sf/four_room/four_room.py
gym_sf/four_room/four_room_goalEnv.py
gym_sf/four_room/render.py
gym_sf/four_room/trial.py
gym_sf/four_room/utilities.py
gym_sf/four_room_multiagent/__init__.py
gym_sf/four_room_multiagent/example_mult.py
gym_sf/four_room_multiagent/four_room_multiagent.py