Metadata-Version: 2.1
Name: gym-sf
Version: 0.1.6
Summary: Environments adapted to the use of successor features
Home-page: https://github.com/rafaelcunha2013/gym-sf
Author: Rafael F Cunha
Author-email: rafaelcunha2013@gmail.com
License: MIT
Platform: UNKNOWN
Requires-Python: >=3.8
License-File: LICENSE.txt
